intrepppid/__init__.py
intrepppid/__main__.py
intrepppid/classifier/__init__.py
intrepppid/classifier/head/__init__.py
intrepppid/classifier/head/mlp.py
intrepppid/cli/__init__.py
intrepppid/cli/train.py
intrepppid/data/__init__.py
intrepppid/data/oma.py
intrepppid/data/ppi.py
intrepppid/data/ppi_oma.py
intrepppid/data/utils.py
intrepppid/e2e/__init__.py
intrepppid/e2e/e2e_triplet.py
intrepppid/encoders/__init__.py
intrepppid/encoders/awd_lstm.py
intrepppid/utils/__init__.py
intrepppid/utils/dictlogger.py
intrepppid/utils/embedding_do.py
intrepppid/utils/weightdrop.py
intrepppid-0.1.0.dist-info/METADATA
intrepppid-0.1.0.dist-info/WHEEL
intrepppid-0.1.0.dist-info/entry_points.txt
intrepppid-0.1.0.dist-info/RECORD
