Metadata-Version: 2.1
Name: intrepppid
Version: 0.1.0
Summary: Protein-protein interaction prediction model that leverages orthology data
Home-page: https://github.com/Emad-COMBINE-lab/intrepppid
License: AGPL-3.0-or-later
Author: Joseph Szymborski
Author-email: joseph.szymborski@mail.mcgill.ca
Requires-Python: >=3.10,<4.0
Classifier: License :: OSI Approved :: GNU Affero General Public License v3 or later (AGPLv3+)
Classifier: Programming Language :: Python :: 3
Classifier: Programming Language :: Python :: 3.10
Classifier: Programming Language :: Python :: 3.11
Requires-Dist: fire (>=0.5.0,<0.6.0)
Requires-Dist: matplotlib (==3.6.3)
Requires-Dist: pandas (==2.2.0)
Requires-Dist: passlib (==1.7.4)
Requires-Dist: plyvel (==1.5.1)
Requires-Dist: pytorch-lightning (==1.9.1)
Requires-Dist: ranger21 (>=0.1.0,<0.2.0)
Requires-Dist: rich (==13.5.2)
Requires-Dist: scikit-learn (==1.2.1)
Requires-Dist: scipy (==1.12.0)
Requires-Dist: sentencepiece (==0.1.97)
Requires-Dist: tables (==3.9.2)
Requires-Dist: tensorboard (==2.15.1)
Requires-Dist: torch (==1.13.1)
Requires-Dist: torchmetrics (==0.11.1)
Requires-Dist: tqdm (==4.64.1)
Project-URL: Repository, https://github.com/Emad-COMBINE-lab/intrepppid
